tests/__init__.py
tests/test_pay.py
toss/__init__.py
toss/client.py
toss/entity.py
toss/exc.py
toss/response.py
toss/validator.py
toss-0.0.4.dist-info/LICENSE
toss-0.0.4.dist-info/METADATA
toss-0.0.4.dist-info/WHEEL
toss-0.0.4.dist-info/top_level.txt
toss-0.0.4.dist-info/RECORD
