Metadata-Version: 2.1
Name: toss
Version: 0.0.4
Summary: Toss payment client library
Home-page: https://github.com/styleshare/toss
Author: Styleshare
Author-email: dev@styleshare.kr
License: UNKNOWN
Platform: UNKNOWN
Classifier: Programming Language :: Python :: 3
Classifier: License :: Public Domain
Classifier: Operating System :: OS Independent
Requires-Dist: inflection (>=0.3.1)
Requires-Dist: pytz (>=2018.7)
Requires-Dist: requests (>=2.20.1)
